lacebuilder/__init__.py
lacebuilder/accuracySvgAndTotals.py
lacebuilder/assess_hocr_dir.py
lacebuilder/cli.py
lacebuilder/dehyphenate.py
lacebuilder/fix_kraken_hocr.py
lacebuilder/generate_spellcheck_file.py
lacebuilder/greek_tools.py
lacebuilder/lacebuilder.py
lacebuilder/spellcheck_hocr.py
lacebuilder/Dictionaries/english_greek_latin.txt
lacebuilder/Dictionaries/greek_and_english.txt
lacebuilder/Dictionaries/greek_and_english_semilunate.txt
lacebuilder/Dictionaries/greek_and_french.txt
lacebuilder/Dictionaries/greek_and_french_and_latin.txt
lacebuilder/Dictionaries/greek_and_latin_semilunate.txt
lacebuilder/Dictionaries/greek_only_from_lg.txt
lacebuilder/Dictionaries/latin_dict.txt
lacebuilder/Dictionaries/latin_greek.txt
lacebuilder/Dictionaries/latin_greek_migne.txt
lacebuilder/Dictionaries/unique_no_accent_list.csv
lacebuilder/XSLT/make_expath_images.xsl
lacebuilder/XSLT/make_expath_texts.xsl
lacebuilder/XSLT/make_meta_images.xsl
lacebuilder/XSLT/make_meta_texts.xsl
lacebuilder/XSLT/make_repo_images.xsl
lacebuilder/XSLT/make_repo_texts.xsl
lacebuilder/XSLT/marc2laceDC.xsl
lacebuilder/static_for_image_xar/collection.xconf
lacebuilder/static_for_image_xar/pre-install.xql
lacebuilder/static_for_text_xar/collection.xconf
lacebuilder/static_for_text_xar/not-post-install.xql
lacebuilder/static_for_text_xar/pre-install.xql
lacebuilder-0.1.2.dist-info/AUTHORS.rst
lacebuilder-0.1.2.dist-info/LICENSE
lacebuilder-0.1.2.dist-info/METADATA
lacebuilder-0.1.2.dist-info/WHEEL
lacebuilder-0.1.2.dist-info/entry_points.txt
lacebuilder-0.1.2.dist-info/top_level.txt
lacebuilder-0.1.2.dist-info/RECORD
