Metadata-Version: 2.1
Name: lacebuilder
Version: 0.1.2
Summary: Lacebuilder generates packages for the Lace OCR editing environment.
Home-page: https://github.com/brobertson/lacebuilder
Author: Bruce Robertson
Author-email: bruce.g.robertson@gmail.com
License: BSD license
Keywords: lacebuilder
Platform: UNKNOWN
Classifier: Development Status :: 2 - Pre-Alpha
Classifier: Intended Audience :: Developers
Classifier: License :: OSI Approved :: BSD License
Classifier: Natural Language :: English
Classifier: Programming Language :: Python :: 3
Classifier: Programming Language :: Python :: 3.5
Classifier: Programming Language :: Python :: 3.6
Classifier: Programming Language :: Python :: 3.7
Classifier: Programming Language :: Python :: 3.8
Requires-Python: >=3.5
Requires-Dist: Click (>=7.0)
Requires-Dist: lxml (==4.6.2)
Requires-Dist: halo (==0.0.31)
Requires-Dist: scikit-image (==0.18.1)
